renderconf/__init__.py
renderconf/cli.py
renderconf/template.py
renderconf/backends/__init__.py
renderconf/backends/aws.py
renderconf/backends/env.py
renderconf-0.4.dist-info/DESCRIPTION.rst
renderconf-0.4.dist-info/entry_points.txt
renderconf-0.4.dist-info/METADATA
renderconf-0.4.dist-info/metadata.json
renderconf-0.4.dist-info/RECORD
renderconf-0.4.dist-info/top_level.txt
renderconf-0.4.dist-info/WHEEL
