Metadata-Version: 2.0
Name: renderconf
Version: 0.4
Summary: A tool for rendering templated configuration files from a variety of data sources
Home-page: http://github.com/slank/renderconf
Author: Matthew Wedgwood
Author-email: mwedgwood@gmail.com
License: MIT
Keywords: configuration,docker,templating
Platform: UNKNOWN
Classifier: Development Status :: 3 - Alpha
Classifier: Topic :: Utilities
Classifier: License :: OSI Approved :: MIT License
Requires-Dist: Jinja2 (==2.8)
Requires-Dist: requests (==2.7.0)
